{
  "products": [
    {
      "id": "1",
      "name": "Stormtrooper",
      "price": 60,
      "image": "/src/imagen1.png"
    },
    {
      "id": "2",
      "name": "Game Boy Classic",
      "price": 60,
      "image": "/src/imagen2.png"
    },
    {
      "id": "3",
      "name": "Stormtrooper",
      "price": 60,
      "image": "/src/imagen1.png"
    },
    {
      "id": "4",
      "name": "Game Boy Classic",
      "price": 60,
      "image": "/src/imagen2.png"
    },
    {
      "id": "6",
      "name": "Stormtrooper",
      "price": 60,
      "image": "/src/imagen1.png"
    },
    {
      "id": "7",
      "name": "Stormtrooper",
      "price": 60,
      "image": "/src/imagen1.png"
    },
    {
      "id": "8",
      "name": "Stormtrooper",
      "price": 60,
      "image": "/src/imagen1.png"
    }
  ]
}